diagonals/__init__.py
diagonals/density.py
diagonals/moc.py
diagonals/ohc.py
diagonals/psi.py
diagonals/regmean.py
diagonals/regsum.py
diagonals/siasie.py
diagonals/zonmean.py
diagonals/examples/__init__.py
diagonals/examples/examples-moc.py
diagonals/examples/examples-oceanheatcontent.py
diagonals/examples/examples-regionmean.py
diagonals/examples/examples-regsum.py
diagonals/examples/examples-siarea.py
diagonals/examples/examples-zonalmean.py
diagonals/mesh_helpers/__init__.py
diagonals/mesh_helpers/nemo.py
test/__init__.py
test/unit/__init__.py
test/unit/test_ohc.py
test/unit/test_regmean.py
diagonals-0.3.2.dist-info/LICENSE
diagonals-0.3.2.dist-info/METADATA
diagonals-0.3.2.dist-info/WHEEL
diagonals-0.3.2.dist-info/top_level.txt
diagonals-0.3.2.dist-info/RECORD
