Metadata-Version: 2.1
Name: diagonals
Version: 0.3.2
Summary: Compute diagnostics targeting the CPU or the GPU
Home-page: https://earth.bsc.es/gitlab/es/diagonals
Author: BSC-CNS Earth Sciences Department
Author-email: saskia.loosveldt@bsc.es
License: UNKNOWN
Platform: UNKNOWN
Classifier: Environment :: Console
Classifier: License :: OSI Approved :: Apache Software License
Classifier: Programming Language :: Python
Classifier: Programming Language :: Python :: 2.7
Classifier: Programming Language :: Python :: 3.6
Requires-Dist: netCDF4
Requires-Dist: numba
Requires-Dist: numpy
Requires-Dist: six
Provides-Extra: gpu
Requires-Dist: pycuda ; extra == 'gpu'
